isddp/__init__.py
isddp/config.py
isddp/py.typed
isddp/_utils/__init__.py
isddp/_utils/formatacao.py
isddp/_utils/leituracsv.py
isddp/sddp/__init__.py
isddp/sddp/convergenciaSDDP.py
isddp/sddp/geracoes.py
isddp/sddp/tabelaSDDP.py
isddp/sddp/modelos/__init__.py
isddp/sddp/modelos/convergenciaSDDP.py
isddp/sddp/modelos/geracoes.py
isddp/sddp/modelos/tabelaSDDP.py
isddp/sddp/modelos/arquivoscsv/__init__.py
isddp/sddp/modelos/arquivoscsv/arquivocsv.py
isddp/sddp/modelos/blocos/__init__.py
isddp/sddp/modelos/blocos/tabelacsv.py
isddp/sddp/modelos/blocos/versaomodelo.py
tests/__init__.py
tests/_arquivos/__init__.py
tests/mocks/__init__.py
tests/mocks/mock_open.py
tests/mocks/arquivos/__init__.py
isddp-1.1.0.dist-info/LICENSE
isddp-1.1.0.dist-info/METADATA
isddp-1.1.0.dist-info/WHEEL
isddp-1.1.0.dist-info/top_level.txt
isddp-1.1.0.dist-info/RECORD
