Metadata-Version: 2.1
Name: isddp
Version: 1.1.0
Summary: Interface para arquivos do SDDP
Home-page: https://github.com/davidAlexander08/isddp
Author: David Alexander
Author-email: david.tbsilva@gmail.com
Classifier: Programming Language :: Python :: 3
Classifier: License :: OSI Approved :: MIT License
Classifier: Operating System :: OS Independent
Classifier: Development Status :: 3 - Alpha
Requires-Python: >=3.8
License-File: LICENSE
Requires-Dist: numpy
Requires-Dist: pandas
Requires-Dist: cfinterface >=1.5.2
